Workbook
Name L_Scenarios: Scenario!$D$10:$D$12
Name Million: Input!$G$15
Name Scenarioused: Scenario!$D$9

Sheet Cover
C7: Nudu Noodles
C8: Financial Model for F2022F to F2026F
C10: Modeller: | D10: Animashaun jafar
C11: Version: | D11: Ver 1.01
C12: Base year | D12: 2021
C14: Circularity: | D14: Net interest expense line of the P&L

Sheet Historical FS
C2: Nudu Noodles
C3: Income Statement
C5: [$'millions]
G7: 2019 | H7: =G7+1 -> 2020 | I7: =H7+1 -> 2021
C9: Revenue growth | E9: [%] | H9: =H13/G13-1 -> -0.0086538462 | I9: =I13/H13-1 -> 0.032007759
C10: COGS [% of revenue] | E10: [%] | G10: =G15/G13 -> 0.31563462 | H10: =H15/H13 -> 0.35790495 | I10: =I15/I13 -> 0.37007519
C11: SG&A [% of revenue] | E11: [%] | G11: =G16/G13 -> 0.19976923 | H11: =H16/H13 -> 0.21132881 | I11: =I16/I13 -> 0.21537594
D13: Revenue | E13: [$'m] | G13: 520 | H13: 515.5 | I13: 532
D15: Cost of sales | E15: [$'m] | G15: 164.13 | H15: 184.5 | I15: 196.88
D16: SG&A | E16: [$'m] | G16: 103.88 | H16: 108.94 | I16: 114.58
D17: Total costs | E17: [$'m] | G17: =SUM(G15:G16) -> 268.01 | H17: =SUM(H15:H16) -> 293.44 | I17: =SUM(I15:I16) -> 311.46
D19: Cost adjustments -Gain/(loss) | E19: [$'m] | G19: -7 | H19: -4.2 | I19: 30
D20: EBITDA | E20: [$'m] | G20: =G13-G17+G19 -> 244.99 | H20: =H13-H17+H19 -> 217.86 | I20: =I13-I17+I19 -> 250.54
D22: Depreciation | E22: [$'m] | G22: 5.1 | H22: 5.5733333 | I22: 5.88
D23: EBIT | E23: [$'m] | G23: =G20-G22 -> 239.89 | H23: =H20-H22 -> 212.28667 | I23: =I20-I22 -> 244.66
D25: Cost adjustments -Gain/(loss) | E25: [$'m] | G25: -58 | H25: -61.95 | I25: -52.9
D26: Net Interest Expense | E26: [$'m] | G26: 62 | H26: 56.6 | I26: 59.1
D27: EBT | E27: [$'m] | G27: =G23+G25-G26 -> 119.89 | H27: =H23+H25-H26 -> 93.736667 | I27: =I23+I25-I26 -> 132.66
D29: Current Taxes | E29: [$'m] | G29: 40.5 | H29: 22.7 | I29: 24.8
D30: Deferred Income Taxes | E30: [$'m] | G30: 16.9 | H30: 31.7 | I30: 24
D31: Total Income Taxes | E31: [$'m] | G31: =SUM(G29:G30) -> 57.4 | H31: =SUM(H29:H30) -> 54.4 | I31: =SUM(I29:I30) -> 48.8
D33: Net Income | E33: [$'m] | G33: =G27-G31 -> 62.49 | H33: =H27-H31 -> 39.336667 | I33: =I27-I31 -> 83.86
D35: Preferred dividend | E35: [$'m] | G35: 0.5 | H35: 0.5 | I35: 0.5
D36: Net Income to Common | E36: [$'m] | G36: =G33-G35 -> 61.99 | H36: =H33-H35 -> 38.836667 | I36: =I33-I35 -> 83.36
C39: Nudu Noodles
C40: Cash Flow Statement
C42: [$'millions]
G43: 2019 | H43: =G43+1 -> 2020 | I43: =H43+1 -> 2021
C44: Operating Activities
D45: Net Income | E45: [$'m] | G45: =G33 -> 62.49 | H45: =H33 -> 39.336667 | I45: =I33 -> 83.86
D46: Depreciation | E46: [$'m] | G46: 5.1 | H46: 5.5733333 | I46: 5.88
D47: Deferred Income Taxes | E47: [$'m] | G47: 1.1266667 | H47: 2.1133333 | I47: 1.6
D48: Changes in Working Capital | E48: [$'m] | G48: -7.9333333 | H48: -0.3 | I48: -5.5866667
D49: Other | E49: [$'m] | G49: 10.793333 | H49: 10.946667 | I49: 16.14
D50: Operating Cash Flow | E50: [$'m] | G50: =SUM(G45:G49) -> 71.576667 | H50: =SUM(H45:H49) -> 57.67 | I50: =SUM(I45:I49) -> 101.89333
C52: Investing Activities
D53: CAPEX | E53: [$'m] | G53: -5.0266667 | H53: -5.38 | I53: -5.5
D54: Asset Dispositions | E54: [$'m] | G54: 0.13333333 | H54: 0.22666667 | I54: 0.7
D55: Other | E55: [$'m] | G55: -0.38666667 | H55: -0.28 | I55: -0.32
D56: Investing Cash Flow | E56: [$'m] | G56: =SUM(G53:G55) -> -5.28 | H56: =SUM(H53:H55) -> -5.4333333 | I56: =SUM(I53:I55) -> -5.12
C58: Financing Activities
D59: Revolver Issuance / (Repayment) | E59: [$'m] | G59: 1 | H59: 0 | I59: 0
D60: Variable Rate Long Term Debt Issuance / (Repayment) | E60: [$'m] | G60: 3.3333333 | H60: 8.3222667 | I60: 0
D61: Fixed Rate Long Term Debt Issuance / (Repayment) | E61: [$'m] | G61: 0 | H61: -6.6666667 | I61: -8.5666667
D62: Preferred Share Issuance/ (Buy-Back) | E62: [$'m] | G62: 0 | H62: 0 | I62: 0
D63: Common Share Issuance/ (Buy-Back) | E63: [$'m] | G63: -5.3666667 | H63: -5.9333333 | I63: -4.6666667
D64: Preferred Dividends | E64: [$'m] | G64: 0 | H64: 0 | I64: 0
D65: Common Dividends | E65: [$'m] | G65: -2.7866667 | H65: -3.0066667 | I65: -3.1266667
D66: Other | E66: [$'m] | G66: -0.12 | H66: -0.12666667 | I66: -0.19333333
D67: Financing Cash Flow | E67: [$'m] | G67: =SUM(G59:G66) -> -3.94 | H67: =SUM(H59:H66) -> -7.4110667 | I67: =SUM(I59:I66) -> -16.553333
D69: Change in Cash Position | E69: [$'m] | G69: =G50+G56+G67 -> 62.356667 | H69: =H50+H56+H67 -> 44.8256 | I69: =I50+I56+I67 -> 80.22
D70: Beginning Cash | E70: [$'m] | G70: 16.16 | H70: =G71 -> 78.516667 | I70: =H71 -> 123.34227
D71: Ending Cash | E71: [$'m] | G71: =SUM(G69:G70) -> 78.516667 | H71: =SUM(H69:H70) -> 123.34227 | I71: =SUM(I69:I70) -> 203.56227
C75: Nudu Noodles
C76: Balance Sheet
C78: [$'millions]
G80: 2019 | H80: =G80+1 -> 2020 | I80: =H80+1 -> 2021
C81: ASSETS
D82: Cash and Equivalents | E82: [$'m] | G82: =G71 -> 78.516667 | H82: =H71 -> 123.34227 | I82: =I71 -> 203.56227
D83: Accounts Receivable | E83: [$'m] | G83: 47.773333 | H83: 50.453333 | I83: 50.56
D84: Inventory | E84: [$'m] | G84: 11.24375 | H84: 12.8775 | I84: 13.57375
D85: Other | E85: [$'m] | G85: 18.426667 | H85: 19.066667 | I85: 19.353333
D86: Total Current Assets | E86: [$'m] | G86: =SUM(G82:G85) -> 155.96042 | H86: =SUM(H82:H85) -> 205.73977 | I86: =SUM(I82:I85) -> 287.04935
D88: Net PP&E | E88: [$'m] | G88: 40.886667 | H88: 34.126667 | I88: 35.773333
D89: Goodwill | E89: [$'m] | G89: 7.7333333 | H89: 7.7266667 | I89: 7.7333333
D90: Intangibles | E90: [$'m] | G90: 14.66 | H90: 14.706667 | I90: 13.86
D91: Other | E91: [$'m] | G91: 11.593333 | H91: 12.966667 | I91: 12.673333
D92: Total Long Term Assets | E92: [$'m] | G92: =SUM(G88:G91) -> 74.873333 | H92: =SUM(H88:H91) -> 69.526667 | I92: =SUM(I88:I91) -> 70.04
D94: Total Assets | E94: [$'m] | G94: =G86+G92 -> 230.83375 | H94: =H86+H92 -> 275.26643 | I94: =I86+I92 -> 357.08935
C96: LIABILITIES AND EQUITY
D97: Bank Debt - Revolver | E97: [$'m] | G97: 0.7 | H97: 0 | I97: 0
D98: Accounts Payable | E98: [$'m] | G98: 18.233333 | H98: 22.613333 | I98: 21.676667
D99: Other | E99: [$'m] | G99: 18.443333 | H99: 19.141667 | I99: 19.436667
D100: Total Current Liabilities | E100: [$'m] | G100: =SUM(G97:G99) -> 37.376667 | H100: =SUM(H97:H99) -> 41.755 | I100: =SUM(I97:I99) -> 41.113333
D102: Variable Rate Long Term Debt | E102: [$'m] | G102: 13.266667 | H102: 13.353333 | I102: 30.533333
D103: Fixed Rate Long Term Debt | E103: [$'m] | G103: 52.526667 | H103: 57.366667 | I103: 25.78
D104: Deferred Income Taxes | E104: [$'m] | G104: 0.93333333 | H104: 1.18 | I104: 1.92
D105: Other | E105: [$'m] | G105: 21.6 | H105: 26.313333 | I105: 27.16
D106: Total Long Term Liabilities | E106: [$'m] | G106: =SUM(G102:G105) -> 88.326667 | H106: =SUM(H102:H105) -> 98.213333 | I106: =SUM(I102:I105) -> 85.393333
D108: Total Liabilities | E108: [$'m] | G108: =G100+G106 -> 125.70333 | H108: =H100+H106 -> 139.96833 | I108: =I100+I106 -> 126.50667
D110: Preferred Shares | E110: [$'m] | G110: 0.42666667 | H110: 0.42666667 | I110: 1.0933333
D111: Common Shares | E111: [$'m] | G111: 24.345333 | H111: 24.801267 | I111: 23.0916
D112: Retained Earnings | E112: [$'m] | G112: 19.637083 | H112: 11.190833 | I112: 23.340417
D113: Other | E113: [$'m] | G113: 60.721333 | H113: 98.879333 | I113: 183.05733
D114: Shareholder's Equity | E114: [$'m] | G114: =SUM(G110:G113) -> 105.13042 | H114: =SUM(H110:H113) -> 135.2981 | I114: =SUM(I110:I113) -> 230.58268
D116: Total Liabilities and Equity | E116: [$'m] | G116: =G108+G114 -> 230.83375 | H116: =H108+H114 -> 275.26643 | I116: =I108+I114 -> 357.08935
D118: Balance check | G118: =G94-G116 -> 3.126388e-13 | H118: =H94-H116 -> 0 | I118: =I94-I116 -> 0

Sheet Summary
B2: =Cover!$C$7 -> Nudu Noodles | I2: ="Financial Forecast "&$L$6&" to "&$P$6 -> Financial Forecast 2022 to 2026
B3: Summary | I3: ="BS Check: "&IF(Model!F115=0,"OK","ERROR") -> BS Check: OK | K3: =Scenarioused -> Scenario: Base Case
I5: Actual | J5: Actual | K5: Actual | L5: Forecast | M5: Forecast | N5: Forecast | O5: Forecast | P5: Forecast
F6: Units | G6: Inputs | I6: =J6-1 -> 2019 | J6: =K6-1 -> 2020 | K6: =Cover!$D$12 -> 2021 | L6: =K6+1 -> 2022 | M6: =L6+1 -> 2023 | N6: =M6+1 -> 2024 | O6: =N6+1 -> 2025 | P6: =O6+1 -> 2026
B8: Analysis based on: Base Case
C10: Revenue
D11: Total Revenue | F11: [$'m] | I11: 520 | J11: 515.5 | K11: 532 | L11: 559.49113 | M11: 652.44489 | N11: 678.17707 | O11: 682.19361 | P11: 734.28792
D12: Growth rate | F12: [%] | J12: -0.0086538462 | K12: 0.032007759 | L12: 0.051675047 | M12: 0.16613983 | N12: 0.039439638 | O12: 0.0059225456 | P12: 0.076362939
C13: Ebitda
D14: Ebitda | F14: [$'m] | I14: 244.99 | J14: 217.86 | K14: 250.54 | L14: 228.52209 | M14: 309.89194 | N14: 325.34754 | O14: 318.07353 | P14: 357.42363
D15: Growth rate | F15: [%] | J15: -0.11073921 | K15: 0.15000459 | L15: -0.087881809 | M15: 0.35606992 | N15: 0.049874164 | O15: -0.022357663 | P15: 0.12371387
D16: ebitda margin | F16: [%] | I16: 0.47113462 | J16: 0.42261882 | K16: 0.47093985 | L16: 0.40844632 | M16: 0.47497029 | N16: 0.47973833 | O16: 0.46625111 | P16: 0.48676224
C17: Net Profit
D18: Net Profit | F18: [$'m] | I18: 62.49 | J18: 39.336667 | K18: 83.86 | L18: 142.52623 | M18: 181.68443 | N18: 174.59943 | O18: 148.73021 | P18: 160.24539
D19: Growth rate | F19: %age | J19: -0.37051262 | K19: 1.1318532 | L19: 0.69957341 | M19: 0.27474386 | N19: -0.038996178 | O19: -0.14816328 | P19: 0.077423256
D20: Net Profit margin | F20: %age | I20: 0.12017308 | J20: 0.076307792 | K20: 0.15763158 | L20: 0.2547426 | M20: 0.27846709 | N20: 0.25745405 | O20: 0.21801759 | P20: 0.21823236
C21: Dupont Analysis
D22: ROE | F22: [%] | I22: 0.59440457 | J22: 0.29074072 | K22: 0.36368733 | L22: 0.39326709 | M22: 0.30884325 | N22: 0.25347678 | O22: 0.18709128 | P22: 0.16696759
D23: Net Profit margin | F23: [%] | I23: 0.12017308 | J23: 0.076307792 | K23: 0.15763158 | L23: 0.2547426 | M23: 0.27846709 | N23: 0.25745405 | O23: 0.21801759 | P23: 0.21823236
D24: Asset turnover | F24: multiples | I24: 2.2527035 | J24: 1.8727311 | K24: 1.4898232 | L24: 1.251074 | M24: 0.82083258 | N24: 0.74364546 | O24: 0.4917252 | P24: 0.55503116
D25: Financial Leverage | F25: multiples | I25: 2.1956895 | J25: 2.0345181 | K25: 1.5486391 | L25: 1.2339655 | M25: 1.3511689 | N25: 1.3239529 | O25: 1.7451773 | P25: 1.3784648
B27: Analysis based on: Best Case
C29: Revenue
D30: Total Revenue | F30: [$'m] | I30: 520 | J30: 515.5 | K30: 532 | L30: 564.59708 | M30: 664.80465 | N30: 699.81243 | O30: 699.58413 | P30: 755.91089
D31: Growth rate | F31: [%] | J31: -0.0086538462 | K31: 0.032007759 | L31: 0.061272697 | M31: 0.17748511 | N31: 0.052658744 | O31: -0.00032622997 | P31: 0.080514638
C32: Ebitda
D33: Ebitda | F33: [$'m] | I33: 244.99 | J33: 217.86 | K33: 250.54 | L33: 232.72043 | M33: 324.63108 | N33: 352.83539 | O33: 344.97359 | P33: 392.43509
D34: Growth rate | F34: [%] | J34: -0.11073921 | K34: 0.15000459 | L34: -0.071124671 | M34: 0.39494023 | N34: 0.086881103 | O34: -0.022281763 | P34: 0.13758009
D35: ebitda margin | F35: [%] | I35: 0.47113462 | J35: 0.42261882 | K35: 0.47093985 | L35: 0.41218851 | M35: 0.48831049 | N35: 0.50418566 | O35: 0.49311238 | P35: 0.51915523
C36: Net Profit
D37: Net Profit | F37: [$'m] | I37: 62.49 | J37: 39.336667 | K37: 83.86 | L37: 145.24995 | M37: 191.2338 | N37: 192.72512 | O37: 166.97717 | P37: 184.19874
D38: Growth rate | F38: %age | J38: -0.37051262 | K38: 1.1318532 | L38: 0.73205278 | M38: 0.3165843 | N38: 0.0077984407 | O38: -0.13359938 | P38: 0.10313732
D39: Net Profit margin | F39: %age | I39: 0.12017308 | J39: 0.076307792 | K39: 0.15763158 | L39: 0.25726302 | M39: 0.28765412 | N39: 0.2753954 | O39: 0.23868061 | P39: 0.24367786
C40: Dupont Analysis
D41: ROE | F41: [%] | I41: 0.59440457 | J41: 0.29074072 | K41: 0.36368733 | L41: 0.39853615 | M41: 0.32006795 | N41: 0.27082691 | O41: 0.20082768 | P41: 0.18162173
D42: Net Profit margin | F42: [%] | I42: 0.12017308 | J42: 0.076307792 | K42: 0.15763158 | L42: 0.25726302 | M42: 0.28765412 | N42: 0.2753954 | O42: 0.23868061 | P42: 0.24367786
D43: Asset turnover | F43: multiples | I43: 2.2527035 | J43: 1.8727311 | K43: 1.4898232 | L43: 1.2561931 | M43: 0.82706064 | N43: 0.76611024 | O43: 0.50400228 | P43: 0.57107041
D44: Financial Leverage | F44: multiples | I44: 2.1956895 | J44: 2.0345181 | K44: 1.5486391 | L44: 1.2332013 | M44: 1.3453468 | N44: 1.2836418 | O44: 1.669452 | P44: 1.305155
B46: Analysis based on: Worst Case
C48: Revenue
D49: Total Revenue | F49: [$'m] | I49: 520 | J49: 515.5 | K49: 532 | L49: 554.40825 | M49: 643.26086 | N49: 665.3573 | O49: 673.40068 | P49: 711.94882
D50: Growth rate | F50: [%] | J50: -0.0086538462 | K50: 0.032007759 | L50: 0.042120771 | M50: 0.16026567 | N50: 0.034350669 | O50: 0.012088813 | P50: 0.05724398
C51: Ebitda
D52: Ebitda | F52: [$'m] | I52: 244.99 | J52: 217.86 | K52: 250.54 | L52: 224.34683 | M52: 296.69637 | N52: 303.19741 | O52: 294.21928 | P52: 313.80834
D53: Growth rate | F53: [%] | J53: -0.11073921 | K53: 0.15000459 | L53: -0.10454685 | M53: 0.32248969 | N53: 0.021911421 | O53: -0.029611516 | P53: 0.066579815
D54: ebitda margin | F54: [%] | I54: 0.47113462 | J54: 0.42261882 | K54: 0.47093985 | L54: 0.40465998 | M54: 0.46123803 | N54: 0.45569112 | O54: 0.43691562 | P54: 0.44077374
C55: Net Profit
D56: Net Profit | F56: [$'m] | I56: 62.49 | J56: 39.336667 | K56: 83.86 | L56: 139.81748 | M56: 173.13673 | N56: 159.97821 | O56: 132.55878 | P56: 130.77392
D57: Growth rate | F57: %age | J57: -0.37051262 | K57: 1.1318532 | L57: 0.66727255 | M57: 0.23830533 | N57: -0.076000714 | O57: -0.17139481 | P57: -0.013464671
D58: Net Profit margin | F58: %age | I58: 0.12017308 | J58: 0.076307792 | K58: 0.15763158 | L58: 0.25219227 | M58: 0.26915477 | N58: 0.24043955 | O58: 0.19684978 | P58: 0.18368444
C59: Dupont Analysis
D60: ROE | F60: [%] | I60: 0.59440457 | J60: 0.29074072 | K60: 0.36368733 | L60: 0.38796773 | M60: 0.2985983 | N60: 0.2389839 | O60: 0.1736372 | P60: 0.14432634
D61: Net Profit margin | F61: [%] | I61: 0.12017308 | J61: 0.076307792 | K61: 0.15763158 | L61: 0.25219227 | M61: 0.26915477 | N61: 0.24043955 | O61: 0.19684978 | P61: 0.18368444
D62: Asset turnover | F62: multiples | I62: 2.2527035 | J62: 1.8727311 | K62: 1.4898232 | L62: 1.2459237 | M62: 0.81748178 | N62: 0.72982472 | O62: 0.48514245 | P62: 0.53812199
D63: Financial Leverage | F63: multiples | I63: 2.1956895 | J63: 2.0345181 | K63: 1.5486391 | L63: 1.2347311 | M63: 1.3570854 | N63: 1.3618967 | O63: 1.8181871 | P63: 1.4601332
A65: Summary Generator:
B66: ="Analysis based on: "&CHOOSE(Scenario!$E$9,Scenario!D10,Scenario!D11,Scenario!D12) -> Analysis based on: Base Case
C68: Revenue
D69: Total Revenue | F69: [$'m] | I69: =Model!I12 -> 520 | J69: =Model!J12 -> 515.5 | K69: =Model!K12 -> 532 | L69: =Model!L12 -> 559.49113 | M69: =Model!M12 -> 652.44489 | N69: =Model!N12 -> 678.17707 | O69: =Model!O12 -> 682.19361 | P69: =Model!P12 -> 734.28792
D70: Growth rate | F70: [%] | J70: =J69/I69-1 -> -0.0086538462 | K70: =K69/J69-1 -> 0.032007759 | L70: =L69/K69-1 -> 0.051675047 | M70: =M69/L69-1 -> 0.16613983 | N70: =N69/M69-1 -> 0.039439638 | O70: =O69/N69-1 -> 0.0059225456 | P70: =P69/O69-1 -> 0.076362939
C71: Ebitda
D72: Ebitda | F72: [$'m] | I72: =Model!I19 -> 244.99 | J72: =Model!J19 -> 217.86 | K72: =Model!K19 -> 250.54 | L72: =Model!L19 -> 228.52209 | M72: =Model!M19 -> 309.89194 | N72: =Model!N19 -> 325.34754 | O72: =Model!O19 -> 318.07353 | P72: =Model!P19 -> 357.42363
D73: Growth rate | F73: [%] | J73: =J72/I72-1 -> -0.11073921 | K73: =K72/J72-1 -> 0.15000459 | L73: =L72/K72-1 -> -0.087881809 | M73: =M72/L72-1 -> 0.35606992 | N73: =N72/M72-1 -> 0.049874164 | O73: =O72/N72-1 -> -0.022357663 | P73: =P72/O72-1 -> 0.12371387
D74: ebitda margin | F74: [%] | I74: =I72/I69 -> 0.47113462 | J74: =J72/J69 -> 0.42261882 | K74: =K72/K69 -> 0.47093985 | L74: =L72/L69 -> 0.40844632 | M74: =M72/M69 -> 0.47497029 | N74: =N72/N69 -> 0.47973833 | O74: =O72/O69 -> 0.46625111 | P74: =P72/P69 -> 0.48676224
C75: Net Profit
D76: Net Profit | F76: [$'m] | I76: =Model!I32 -> 62.49 | J76: =Model!J32 -> 39.336667 | K76: =Model!K32 -> 83.86 | L76: =Model!L32 -> 142.08742 | M76: =Model!M32 -> 181.24776 | N76: =Model!N32 -> 174.59243 | O76: =Model!O32 -> 148.71173 | P76: =Model!P32 -> 160.22652
D77: Growth rate | F77: %age | J77: =J76/I76-1 -> -0.37051262 | K77: =K76/J76-1 -> 1.1318532 | L77: =L76/K76-1 -> 0.69434086 | M77: =M76/L76-1 -> 0.27560735 | N77: =N76/M76-1 -> -0.036719563 | O77: =O76/N76-1 -> -0.14823491 | P77: =P76/O76-1 -> 0.077430274
D78: Net Profit margin | F78: %age | I78: =I76/I69 -> 0.12017308 | J78: =J76/J69 -> 0.076307792 | K78: =K76/K69 -> 0.15763158 | L78: =L76/L69 -> 0.25395832 | M78: =M76/M69 -> 0.27779782 | N78: =N76/N69 -> 0.25744371 | O78: =O76/O69 -> 0.21799051 | P78: =P76/P69 -> 0.21820667
C79: Dupont Analysis
D80: =Model!D39 -> ROE | F80: =Model!F39 -> [%] | I80: =Model!I39 -> 0.59440457 | J80: =Model!J39 -> 0.29074072 | K80: =Model!K39 -> 0.36368733 | L80: =Model!L39 -> 0.39241266 | M80: =Model!M39 -> 0.30844524 | N80: =Model!N39 -> 0.25371039 | O80: =Model!O39 -> 0.18722718 | P80: =Model!P39 -> 0.16706803
D81: =Model!D40 -> Net Profit margin | F81: =Model!F40 -> [%] | I81: =Model!I40 -> 0.12017308 | J81: =Model!J40 -> 0.076307792 | K81: =Model!K40 -> 0.15763158 | L81: =Model!L40 -> 0.25395832 | M81: =Model!M40 -> 0.27779782 | N81: =Model!N40 -> 0.25744371 | O81: =Model!O40 -> 0.21799051 | P81: =Model!P40 -> 0.21820667
D82: =Model!D41 -> Asset turnover | F82: =Model!F41 -> multiples | I82: =Model!I41 -> 2.2527035 | J82: =Model!J41 -> 1.8727311 | K82: =Model!K41 -> 1.4898232 | L82: =Model!L41 -> 1.1837085 | M82: =Model!M41 -> 0.8215112 | N82: =Model!N41 -> 0.74364546 | O82: =Model!O41 -> 0.4917252 | P82: =Model!P41 -> 0.55503116
D83: =Model!D42 -> Financial Leverage | F83: =Model!F42 -> multiples | I83: =Model!I42 -> 2.1956895 | J83: =Model!J42 -> 2.0345181 | K83: =Model!K42 -> 1.5486391 | L83: =Model!L42 -> 1.3053766 | M83: =Model!M42 -> 1.3515613 | N83: =Model!N42 -> 1.3252262 | O83: =Model!O42 -> 1.7466619 | P83: =Model!P42 -> 1.3794563

Sheet Input
B2: =Cover!$C$7 -> Nudu Noodles | I2: ="Financial Forecast "&$L$6&" to "&$P$6 -> Financial Forecast 2022 to 2026
B3: Input | I3: ="BS Check: "&IF(Model!F115=0,"OK","ERROR") -> BS Check: OK | K3: =Scenarioused -> Scenario: Base Case
I5: Actual | J5: Actual | K5: Actual | L5: Forecast | M5: Forecast | N5: Forecast | O5: Forecast | P5: Forecast
F6: Units | G6: Inputs | I6: =J6-1 -> 2019 | J6: =K6-1 -> 2020 | K6: =Cover!$D$12 -> 2021 | L6: =K6+1 -> 2022 | M6: =L6+1 -> 2023 | N6: =M6+1 -> 2024 | O6: =N6+1 -> 2025 | P6: =O6+1 -> 2026
B8: General Assumptions
D10: Days in the period | I10: =DATE(I6,12,31)-DATE(I6,1,1)+1 -> 365 | J10: =DATE(J6,12,31)-DATE(J6,1,1)+1 -> 366 | K10: =DATE(K6,12,31)-DATE(K6,1,1)+1 -> 365 | L10: =DATE(L6,12,31)-DATE(L6,1,1)+1 -> 365 | M10: =DATE(M6,12,31)-DATE(M6,1,1)+1 -> 365 | N10: =DATE(N6,12,31)-DATE(N6,1,1)+1 -> 366 | O10: =DATE(O6,12,31)-DATE(O6,1,1)+1 -> 365 | P10: =DATE(P6,12,31)-DATE(P6,1,1)+1 -> 365
C12: Style Guide
D13: Number | G13: 1234
D15: Millions | G15: 1000000
D16: Inputs | G16: 12345
D17: Percent | G17: 0.055
D18: Multiple | G18: 12
D19: Linked cells | G19: 12345
D20: Units | G20: [$'m]
D21: Total | G21: Text
D22: Headings 2 | G22: Text
B25: Revenue Assumptions
C27: Product-70g
D28: Production Capacity | F28: [units] | L28: 35000000 | M28: 35000000 | N28: 35000000 | O28: 33000000 | P28: 35000000
D29: Price | K29: 15
D30: Pricing growth | F30: [%] | L30: =Scenario!L16 -> 0.025 | M30: =Scenario!M16 -> 0.022 | N30: =Scenario!N16 -> 0.02 | O30: =Scenario!O16 -> 0.013 | P30: =Scenario!P16 -> 0.025
D31: Volume growth | F31: [%] | L31: =Scenario!L22 -> 0.03 | M31: =Scenario!M22 -> 0.035 | N31: =Scenario!N22 -> 0.02 | O31: =Scenario!O22 -> 0.025 | P31: =Scenario!P22 -> 0.03
C33: Product-100g
D34: =D28 -> Production Capacity | F34: [units] | M34: 4600000 | N34: 4600000 | O34: 4000000 | P34: 3800000
D35: Price | F35: [$/unit] | M35: 18
D36: Pricing growth | F36: [%] | N36: =Scenario!N29 -> 0.028 | O36: =Scenario!O29 -> 0.013 | P36: =Scenario!P29 -> 0.02
D37: Volume | F37: [units] | M37: 3500000
D38: Volume growth | F38: [%] | N38: =Scenario!N34 -> 0.02 | O38: =Scenario!O34 -> 0.025 | P38: =Scenario!P34 -> 0.03
C40: Auxillary Revenue
D41: Auxillary Sales | F41: [$'m] | K41: 70.5
D42: Auxillary Sales growth | F42: [%] | L42: =Scenario!L40 -> 0.025 | M42: =Scenario!M40 -> 0.025 | N42: =Scenario!N40 -> 0.025 | O42: =Scenario!O40 -> 0.025 | P42: =Scenario!P40 -> 0.025
B44: Production Cost Assumptions
C46: Variable Costs
D47: Wheat | F47: $/unit | L47: 2.8
D48: Potatoes Starch | F48: $/unit | L48: 1.2
D49: Other raw materials | F49: $/unit | L49: 1.9
D50: Total Variable Cost per unit | F50: $/unit | L50: =SUM(L47:L49) -> 5.9
C52: Aggregate Fixed Cost
D53: Capital Charges | F53: [$'m] | L53: 10.5
D54: Labour | F54: [$'m] | L54: 3.2
D55: Other Costs | F55: [$'m] | L55: 5.1
D56: Aggregate Fixed Cost | F56: [$'m] | L56: =SUM(L53:L55) -> 18.8
D58: Cost Inflation | F58: [%] | L58: =Scenario!L46 -> 0.02 | M58: =Scenario!M46 -> 0.035 | N58: =Scenario!N46 -> 0.03 | O58: =Scenario!O46 -> 0.032 | P58: =Scenario!P46 -> 0.035
D60: SG&A | F60: [$'m] | L60: 125.2
B62: Capex, Depreciation & Amortization
D64: Capex | F64: [$'m] | L64: 75 | M64: 550 | N64: 200 | O64: 550 | P64: 25.5
D66: Depreciation method | F66: Straight Line
C68: Useful life of Assets
D69: Remaining Assets | F69: [years] | G69: 10
D70: New Assets | F70: [years] | G70: 15
B72: Working Capital Assumptions
D74: Days in the year | I74: =I10 -> 365 | J74: =J10 -> 366 | K74: =K10 -> 365 | L74: =L10 -> 365 | M74: =M10 -> 365 | N74: =N10 -> 366 | O74: =O10 -> 365 | P74: =P10 -> 365
C76: Exract from Financials
D77: Revenue | F77: [$'m] | I77: ='Historical FS'!G13 -> 520 | J77: ='Historical FS'!H13 -> 515.5 | K77: ='Historical FS'!I13 -> 532
D78: Cost of sales | F78: [$'m] | I78: ='Historical FS'!G15 -> 164.13 | J78: ='Historical FS'!H15 -> 184.5 | K78: ='Historical FS'!I15 -> 196.88
C80: Account Balances
D81: Accounts Receivable | F81: [$'m] | I81: ='Historical FS'!G83 -> 47.773333 | J81: ='Historical FS'!H83 -> 50.453333 | K81: ='Historical FS'!I83 -> 50.56
D82: Inventory | F82: [$'m] | I82: ='Historical FS'!G84 -> 11.24375 | J82: ='Historical FS'!H84 -> 12.8775 | K82: ='Historical FS'!I84 -> 13.57375
D83: Other current Assets | F83: [$'m] | I83: ='Historical FS'!G85 -> 18.426667 | J83: ='Historical FS'!H85 -> 19.066667 | K83: ='Historical FS'!I85 -> 19.353333
D84: Accounts Payable | F84: [$'m] | I84: ='Historical FS'!G98 -> 18.233333 | J84: ='Historical FS'!H98 -> 22.613333 | K84: ='Historical FS'!I98 -> 21.676667
D85: Other Current Liabilities | F85: [$'m] | I85: ='Historical FS'!G99 -> 18.443333 | J85: ='Historical FS'!H99 -> 19.141667 | K85: ='Historical FS'!I99 -> 19.436667
C87: Days
D88: =D81 -> Accounts Receivable | F88: [days] | I88: =I$81/I$77*I$74 -> 33.533205 | J88: =J$81/J$77*J$74 -> 35.821377 | K88: =K$81/K$77*K$74 -> 34.688722 | L88: 34.7 | M88: 35.1 | N88: 34.8 | O88: 34.9 | P88: 34.9
D89: =D82 -> Inventory | F89: [days] | I89: =I82/I$78*I$74 -> 25.004379 | J89: =J82/J$78*J$74 -> 25.54561 | K89: =K82/K$78*K$74 -> 25.164662 | L89: 25.2 | M89: 25.3 | N89: 25.2 | O89: 25.2 | P89: 25.2
D90: =D83 -> Other current Assets | F90: [days] | I90: =I83/I$78*I$74 -> 40.978086 | J90: =J83/J$78*J$74 -> 37.823306 | K90: =K83/K$78*K$74 -> 35.879554 | L90: 38.2 | M90: 37.3 | N90: 37.1 | O90: 37.5 | P90: 37.3
D91: =D84 -> Accounts Payable | F91: [days] | I91: =I84/I$78*I$74 -> 40.548143 | J91: =J84/J$78*J$74 -> 44.85897 | K91: =K84/K$78*K$74 -> 40.186831 | L91: 41.9 | M91: 42.3 | N91: 41.5 | O91: 41.9 | P91: 41.9
D92: =D85 -> Other Current Liabilities | F92: [days] | I92: =I85/I$78*I$74 -> 41.015151 | J92: =J85/J$78*J$74 -> 37.972087 | K92: =K85/K$78*K$74 -> 36.034048 | L92: 38.3 | M92: 37.4 | N92: 37.2 | O92: 37.6 | P92: 37.4
B94: Tax Assumptions
D96: Company Tax rate | F96: [%] | L96: 0.35 | M96: 0.35 | N96: 0.35 | O96: 0.35 | P96: 0.35
D98: Reduction in EBT due to timing differences | F98: [$'m] | L98: 30 | M98: 30 | N98: 30 | O98: 30 | P98: 30
B100: Debt & Interest Rate Assumptions
C102: Interest rates
D103: Fixed rate term debt | F103: [%] | G103: 0.0425 | L103: =G103 -> 0.0425 | M103: =L103 -> 0.0425 | N103: =M103 -> 0.0425 | O103: =N103 -> 0.0425 | P103: =O103 -> 0.0425
D105: Revolver | F105: [%] | G105: 0.0425 | L105: =G105 -> 0.0425 | M105: =L105 -> 0.0425 | N105: =M105 -> 0.0425 | O105: =N105 -> 0.0425 | P105: =O105 -> 0.0425
D107: Variable rate term debt | F107: [%] | G107: 0.0225 | L107: =G107 -> 0.0225 | M107: =L107 -> 0.0225 | N107: =M107 -> 0.0225 | O107: =N107 -> 0.0225 | P107: =O107 -> 0.0225
D109: LIBOR | F109: [%] | G109: 0.011 | L109: =G109 -> 0.011 | M109: =L109 -> 0.011 | N109: =M109 -> 0.011 | O109: =N109 -> 0.011 | P109: =O109 -> 0.011
D111: Excess Cash | F111: [%] | G111: 0.01 | L111: =G111 -> 0.01 | M111: =L111 -> 0.01 | N111: =M111 -> 0.01 | O111: =N111 -> 0.01 | P111: =O111 -> 0.01
C113: Amortization/repayment on debt
D114: Fixed rate term debt: Issuance | F114: [$'m] | L114: 0 | M114: 80 | N114: 0 | O114: 0 | P114: 0
D115: Fixed rate term debt: repayment | L115: 0 | M115: 50 | N115: 50 | O115: 50 | P115: 50
D117: Variable rate term debt: Issuance | F117: [$'m] | L117: 0 | M117: 30 | N117: 0 | O117: 30 | P117: 0
D118: Variable rate term debt: repayment | L118: 90 | M118: 90 | N118: 90 | O118: 90 | P118: 90
B120: Equity Assumptions
C122: Preferred Shares
D123: Issuance/(buyback) | F123: [$'m] | L123: 0 | M123: 95 | N123: 0 | O123: 0 | P123: 0
D125: Yield on Preference | F125: [%] | L125: 0.075 | M125: 0.075 | N125: 0.075 | O125: 0.075 | P125: 0.075
C127: Common Shares
D128: Issuance/(buyback) | F128: [$'m] | L128: 25 | M128: 0 | N128: -25 | O128: 0 | P128: 50
D129: Dividend payout ratio | F129: [%] | L129: 0.25 | M129: 0.25 | N129: 0.25 | O129: 0.25 | P129: 0.25
C131: Other Assumptions
D133: Cost adjustments -Gain/(loss)-from operations | F133: [$'m] | L133: 0 | M133: 0 | N133: 0 | O133: 0 | P133: 0
D134: Cost adjustments -Gain/(loss)-from financing | F134: [$'m] | L134: 0 | M134: 0 | N134: 0 | O134: 0 | P134: 0
D135: Other operating Cashflow activities | F135: [$'m] | L135: 0 | M135: 0 | N135: 0 | O135: 0 | P135: 0
D136: Other investing Cashflow activities | F136: [$'m] | L136: 0 | M136: 0 | N136: 0 | O136: 0 | P136: 0
D137: Other Financing Cashflow activities | F137: [$'m] | L137: 0 | M137: 0 | N137: 0 | O137: 0 | P137: 0
D138: Other Longterm Assets | F138: [$'m] | L138: 0 | M138: 0 | N138: 0 | O138: 0 | P138: 0
D139: Other Longterm Liabilities | F139: [$'m] | L139: 0 | M139: 0 | N139: 0 | O139: 0 | P139: 0
D140: Other shareholders equity | F140: [$'m] | L140: 0 | M140: 0 | N140: 0 | O140: 0 | P140: 0
D141: Cash reserve minimum requirements | F141: [$'m] | L141: 0 | M141: 0 | N141: 0 | O141: 0 | P141: 0
D142: Asset dispositions | F142: [$'m] | L142: 0 | M142: 0 | N142: 0 | O142: 0 | P142: 0
...

Sheet Scenario
B2: =Cover!$C$7 -> Nudu Noodles | I2: ="Financial Forecast "&$L$6&" to "&$P$6 -> Financial Forecast 2022 to 2026
B3: Scenario | I3: ="BS Check: "&IF(Model!F115=0,"OK","ERROR") -> BS Check: OK | K3: =Scenarioused -> Scenario: Base Case
I5: Actual | J5: Actual | K5: Actual | L5: Forecast | M5: Forecast | N5: Forecast | O5: Forecast | P5: Forecast
F6: Units | G6: Inputs | I6: =J6-1 -> 2019 | J6: =K6-1 -> 2020 | K6: =Cover!$D$12 -> 2021 | L6: =K6+1 -> 2022 | M6: =L6+1 -> 2023 | N6: =M6+1 -> 2024 | O6: =N6+1 -> 2025 | P6: =O6+1 -> 2026
B8: Scenario List
D9: ="Scenario: "&CHOOSE($E$9,D10,D11,D12) -> Scenario: Base Case | E9: 1
D10: Base Case
D11: Best Case
D12: Worst Case
B15: Pricing growth-70g
C16: Used in the model | F16: [%] | L16: =CHOOSE($E$9,L17,L18,L19) -> 0.025 | M16: =CHOOSE($E$9,M17,M18,M19) -> 0.022 | N16: =CHOOSE($E$9,N17,N18,N19) -> 0.02 | O16: =CHOOSE($E$9,O17,O18,O19) -> 0.013 | P16: =CHOOSE($E$9,P17,P18,P19) -> 0.025
D17: Base Case | F17: [%] | L17: 0.025 | M17: 0.022 | N17: 0.02 | O17: 0.013 | P17: 0.025
D18: Best Case | F18: [%] | L18: 0.03 | M18: 0.03 | N18: 0.03 | O18: 0.018 | P18: 0.03
D19: Worst Case | F19: [%] | L19: 0.02 | M19: 0.02 | N19: 0.02 | O19: 0.008 | P19: 0.02
B21: Volume growth-70g
C22: Used in the model | F22: [%] | L22: =CHOOSE($E$9,L23,L24,L25) -> 0.03 | M22: =CHOOSE($E$9,M23,M24,M25) -> 0.035 | N22: =CHOOSE($E$9,N23,N24,N25) -> 0.02 | O22: =CHOOSE($E$9,O23,O24,O25) -> 0.025 | P22: =CHOOSE($E$9,P23,P24,P25) -> 0.03
D23: Base Case | F23: [%] | L23: 0.03 | M23: 0.035 | N23: 0.02 | O23: 0.025 | P23: 0.03
D24: Best Case | F24: [%] | L24: 0.035 | M24: 0.04 | N24: 0.025 | O24: 0.03 | P24: 0.035
D25: Worst Case | F25: [%] | L25: 0.025 | M25: 0.03 | N25: 0.015 | O25: 0.02 | P25: 0.025
B27: Pricing growth-100g
C28: Used in the model | F28: [%] | L28: =CHOOSE($E$9,L29,L30,L31) -> 0 | M28: =CHOOSE($E$9,M29,M30,M31) -> 0 | N28: =CHOOSE($E$9,N29,N30,N31) -> 0.028 | O28: =CHOOSE($E$9,O29,O30,O31) -> 0.013 | P28: =CHOOSE($E$9,P29,P30,P31) -> 0.02
D29: Base Case | F29: [%] | N29: 0.028 | O29: 0.013 | P29: 0.02
D30: Best Case | F30: [%] | N30: 0.033 | O30: 0.018 | P30: 0.025
D31: Worst Case | F31: [%] | N31: 0.023 | O31: 0.008 | P31: 0.015
B33: Volume growth-100g
C34: Used in the model | F34: [%] | L34: =CHOOSE($E$9,L35,L36,L37) -> 0 | M34: =CHOOSE($E$9,M35,M36,M37) -> 0 | N34: =CHOOSE($E$9,N35,N36,N37) -> 0.02 | O34: =CHOOSE($E$9,O35,O36,O37) -> 0.025 | P34: =CHOOSE($E$9,P35,P36,P37) -> 0.03
D35: Base Case | F35: [%] | L35: 0 | M35: 0 | N35: 0.02 | O35: 0.025 | P35: 0.03
D36: Best Case | F36: [%] | L36: 0 | M36: 0 | N36: 0.025 | O36: 0.035 | P36: 0.04
D37: Worst Case | F37: [%] | L37: 0 | M37: 0 | N37: 0.015 | O37: 0.015 | P37: 0.015
B39: Auxillary Sales growth
C40: Used in the model | F40: [%] | L40: =CHOOSE($E$9,L41,L42,L43) -> 0.025 | M40: =CHOOSE($E$9,M41,M42,M43) -> 0.025 | N40: =CHOOSE($E$9,N41,N42,N43) -> 0.025 | O40: =CHOOSE($E$9,O41,O42,O43) -> 0.025 | P40: =CHOOSE($E$9,P41,P42,P43) -> 0.025
D41: Base Case | F41: [%] | L41: 0.025 | M41: 0.025 | N41: 0.025 | O41: 0.025 | P41: 0.025
D42: Best Case | F42: [%] | L42: 0.03 | M42: 0.03 | N42: 0.03 | O42: 0.03 | P42: 0.03
D43: Worst Case | F43: [%] | L43: 0.02 | M43: 0.02 | N43: 0.02 | O43: 0.02 | P43: 0.02
B45: Cost Inflation
C46: Used in the model | F46: [%] | L46: =CHOOSE($E$9,L47,L48,L49) -> 0.02 | M46: =CHOOSE($E$9,M47,M48,M49) -> 0.035 | N46: =CHOOSE($E$9,N47,N48,N49) -> 0.03 | O46: =CHOOSE($E$9,O47,O48,O49) -> 0.032 | P46: =CHOOSE($E$9,P47,P48,P49) -> 0.035
D47: Base Case | F47: [%] | L47: 0.02 | M47: 0.035 | N47: 0.03 | O47: 0.032 | P47: 0.035
D48: Best Case | F48: [%] | L48: 0.01 | M48: 0.025 | N48: 0.02 | O48: 0.022 | P48: 0.025
D49: Worst Case | F49: [%] | L49: 0.035 | M49: 0.05 | N49: 0.045 | O49: 0.047 | P49: 0.05

Sheet Model
B2: =Cover!$C$7 -> Nudu Noodles | I2: ="Financial Forecast "&$L$6&" to "&$P$6 -> Financial Forecast 2022 to 2026
B3: Model | I3: ="BS Check: "&IF(Model!F115=0,"OK","ERROR") -> BS Check: OK | K3: =Scenarioused -> Scenario: Base Case
I5: Actual | J5: Actual | K5: Actual | L5: Forecast | M5: Forecast | N5: Forecast | O5: Forecast | P5: Forecast
F6: Units | G6: Inputs | I6: =J6-1 -> 2019 | J6: =K6-1 -> 2020 | K6: =Cover!$D$12 -> 2021 | L6: =K6+1 -> 2022 | M6: =L6+1 -> 2023 | N6: =M6+1 -> 2024 | O6: =N6+1 -> 2025 | P6: =O6+1 -> 2026
A8: Financial Statements
B10: Income Statement
D12: ='Historical FS'!D13 -> Revenue | F12: ='Historical FS'!E13 -> [$'m] | I12: ='Historical FS'!G13 -> 520 | J12: ='Historical FS'!H13 -> 515.5 | K12: ='Historical FS'!I13 -> 532 | L12: =L157 -> 559.49113 | M12: =M157 -> 652.44489 | N12: =N157 -> 678.17707 | O12: =O157 -> 682.19361 | P12: =P157 -> 734.28792
D14: ='Historical FS'!D15 -> Cost of sales | I14: ='Historical FS'!G15 -> 164.13 | J14: ='Historical FS'!H15 -> 184.5 | K14: ='Historical FS'!I15 -> 196.88 | L14: =L191 -> 205.76903 | M14: =M191 -> 212.97095 | N14: =N191 -> 219.36008 | O14: =O191 -> 226.3796 | P14: =P191 -> 234.30289
D15: ='Historical FS'!D16 -> SG&A | F15: ='Historical FS'!E16 -> [$'m] | I15: ='Historical FS'!G16 -> 103.88 | J15: ='Historical FS'!H16 -> 108.94 | K15: ='Historical FS'!I16 -> 114.58 | L15: =L193 -> 125.2 | M15: =M193 -> 129.582 | N15: =N193 -> 133.46946 | O15: =O193 -> 137.74048 | P15: =P193 -> 142.5614
D16: ='Historical FS'!D17 -> Total costs | F16: ='Historical FS'!E17 -> [$'m] | I16: =SUM(I14:I15) -> 268.01 | J16: =SUM(J14:J15) -> 293.44 | K16: =SUM(K14:K15) -> 311.46 | L16: =SUM(L14:L15) -> 330.96903 | M16: =SUM(M14:M15) -> 342.55295 | N16: =SUM(N14:N15) -> 352.82954 | O16: =SUM(O14:O15) -> 364.12008 | P16: =SUM(P14:P15) -> 376.86429
D18: ='Historical FS'!D19 -> Cost adjustments -Gain/(loss) | F18: ='Historical FS'!E19 -> [$'m] | I18: ='Historical FS'!G19 -> -7 | J18: ='Historical FS'!H19 -> -4.2 | K18: ='Historical FS'!I19 -> 30 | L18: =Input!L133 -> 0 | M18: =Input!M133 -> 0 | N18: =Input!N133 -> 0 | O18: =Input!O133 -> 0 | P18: =Input!P133 -> 0
D19: ='Historical FS'!D20 -> EBITDA | F19: ='Historical FS'!E20 -> [$'m] | I19: =I12-I16+I18 -> 244.99 | J19: =J12-J16+J18 -> 217.86 | K19: =K12-K16+K18 -> 250.54 | L19: =L12-L16+L18 -> 228.52209 | M19: =M12-M16+M18 -> 309.89194 | N19: =N12-N16+N18 -> 325.34754 | O19: =O12-O16+O18 -> 318.07353 | P19: =P12-P16+P18 -> 357.42363
D21: ='Historical FS'!D22 -> Depreciation | F21: ='Historical FS'!E22 -> [$'m] | I21: ='Historical FS'!G22 -> 5.1 | J21: ='Historical FS'!H22 -> 5.5733333 | K21: ='Historical FS'!I22 -> 5.88 | L21: =L215 -> 6.0773333 | M21: =M215 -> 26.910667 | N21: =N215 -> 51.910667 | O21: =O215 -> 76.910667 | P21: =P215 -> 96.094
D22: ='Historical FS'!D23 -> EBIT | F22: ='Historical FS'!E23 -> [$'m] | I22: =I19-I21 -> 239.89 | J22: =J19-J21 -> 212.28667 | K22: =K19-K21 -> 244.66 | L22: =L19-L21 -> 222.44476 | M22: =M19-M21 -> 282.98127 | N22: =N19-N21 -> 273.43687 | O22: =O19-O21 -> 241.16286 | P22: =P19-P21 -> 261.32963
D24: ='Historical FS'!D25 -> Cost adjustments -Gain/(loss) | F24: ='Historical FS'!E25 -> [$'m] | I24: ='Historical FS'!G25 -> -58 | J24: ='Historical FS'!H25 -> -61.95 | K24: ='Historical FS'!I25 -> -52.9 | L24: =Input!L134 -> 0 | M24: =Input!M134 -> 0 | N24: =Input!N134 -> 0 | O24: =Input!O134 -> 0 | P24: =Input!P134 -> 0
D25: ='Historical FS'!D26 -> Net Interest Expense | F25: ='Historical FS'!E26 -> [$'m] | I25: ='Historical FS'!G26 -> 62 | J25: ='Historical FS'!H26 -> 56.6 | K25: ='Historical FS'!I26 -> 59.1 | L25: =L344 -> 3.8487203 | M25: =M344 -> 4.1385551 | N25: =N344 -> 4.8331392 | O25: =O344 -> 12.375578 | P25: =P344 -> 14.827289
D26: ='Historical FS'!D27 -> EBT | F26: ='Historical FS'!E27 -> [$'m] | I26: =I22+I24-I25 -> 119.89 | J26: =J22+J24-J25 -> 93.736667 | K26: =K22+K24-K25 -> 132.66 | L26: =L22+L24-L25 -> 218.59604 | M26: =M22+M24-M25 -> 278.84271 | N26: =N22+N24-N25 -> 268.60373 | O26: =O22+O24-O25 -> 228.78728 | P26: =P22+P24-P25 -> 246.50234
D28: ='Historical FS'!D29 -> Current Taxes | F28: ='Historical FS'!E29 -> [$'m] | I28: ='Historical FS'!G29 -> 40.5 | J28: ='Historical FS'!H29 -> 22.7 | K28: ='Historical FS'!I29 -> 24.8 | L28: =L227 -> 66.008613 | M28: =M227 -> 87.09495 | N28: =N227 -> 83.511306 | O28: =O227 -> 69.575549 | P28: =P227 -> 75.77582
D29: ='Historical FS'!D30 -> Deferred Income Taxes | F29: ='Historical FS'!E30 -> [$'m] | I29: ='Historical FS'!G30 -> 16.9 | J29: ='Historical FS'!H30 -> 31.7 | K29: ='Historical FS'!I30 -> 24 | L29: =L228 -> 10.5 | M29: =M228 -> 10.5 | N29: =N228 -> 10.5 | O29: =O228 -> 10.5 | P29: =P228 -> 10.5
D30: ='Historical FS'!D31 -> Total Income Taxes | F30: ='Historical FS'!E31 -> [$'m] | I30: =SUM(I28:I29) -> 57.4 | J30: =SUM(J28:J29) -> 54.4 | K30: =SUM(K28:K29) -> 48.8 | L30: =SUM(L28:L29) -> 76.508613 | M30: =SUM(M28:M29) -> 97.59495 | N30: =SUM(N28:N29) -> 94.011306 | O30: =SUM(O28:O29) -> 80.075549 | P30: =SUM(P28:P29) -> 86.27582
D32: ='Historical FS'!D33 -> Net Income | F32: ='Historical FS'!E33 -> [$'m] | I32: =I26-I30 -> 62.49 | J32: =J26-J30 -> 39.336667 | K32: =K26-K30 -> 83.86 | L32: =L26-L30 -> 142.08742 | M32: =M26-M30 -> 181.24776 | N32: =N26-N30 -> 174.59243 | O32: =O26-O30 -> 148.71173 | P32: =P26-P30 -> 160.22652
D34: ='Historical FS'!D35 -> Preferred dividend | F34: ='Historical FS'!E35 -> [$'m] | I34: ='Historical FS'!G35 -> 0.5 | J34: ='Historical FS'!H35 -> 0.5 | K34: ='Historical FS'!I35 -> 0.5 | L34: =L270 -> 0.082 | M34: =M270 -> 7.207 | N34: =N270 -> 7.207 | O34: =O270 -> 7.207 | P34: =P270 -> 7.207
D35: ='Historical FS'!D36 -> Net Income to Common | F35: ='Historical FS'!E36 -> [$'m] | I35: =I32-I34 -> 61.99 | J35: =J32-J34 -> 38.836667 | K35: =K32-K34 -> 83.36 | L35: =L32-L34 -> 142.00542 | M35: =M32-M34 -> 174.04076 | N35: =N32-N34 -> 167.38543 | O35: =O32-O34 -> 141.50473 | P35: =P32-P34 -> 153.01952
D37: EBITDA margin | F37: [%] | I37: =I19/I12 -> 0.47113462 | J37: =J19/J12 -> 0.42261882 | K37: =K19/K12 -> 0.47093985 | L37: =L19/L12 -> 0.40844632 | M37: =M19/M12 -> 0.47497029 | N37: =N19/N12 -> 0.47973833 | O37: =O19/O12 -> 0.46625111 | P37: =P19/P12 -> 0.48676224
D38: Dupont Analysis
D39: ROE | F39: [%] | I39: =I32/I111 -> 0.59440457 | J39: =J32/J111 -> 0.29074072 | K39: =K32/K111 -> 0.36368733 | L39: =L32/L111 -> 0.39241266 | M39: =M32/M111 -> 0.30844524 | N39: =N32/N111 -> 0.25371039 | O39: =O32/O111 -> 0.18722718 | P39: =P32/P111 -> 0.16706803
D40: Net Profit margin | F40: [%] | I40: =I32/I12 -> 0.12017308 | J40: =J32/J12 -> 0.076307792 | K40: =K32/K12 -> 0.15763158 | L40: =L32/L12 -> 0.25395832 | M40: =M32/M12 -> 0.27779782 | N40: =N32/N12 -> 0.25744371 | O40: =O32/O12 -> 0.21799051 | P40: =P32/P12 -> 0.21820667
D41: Asset turnover | F41: multiples | I41: =I12/I91 -> 2.2527035 | J41: =J12/J91 -> 1.8727311 | K41: =K12/K91 -> 1.4898232 | L41: =L12/L91 -> 1.1837085 | M41: =M12/M91 -> 0.8215112 | N41: =N12/N91 -> 0.74364546 | O41: =O12/O91 -> 0.4917252 | P41: =P12/P91 -> 0.55503116
D42: Financial Leverage | F42: multiples | I42: =I91/I111 -> 2.1956895 | J42: =J91/J111 -> 2.0345181 | K42: =K91/K111 -> 1.5486391 | L42: =L91/L111 -> 1.3053766 | M42: =M91/M111 -> 1.3515613 | N42: =N91/N111 -> 1.3252262 | O42: =O91/O111 -> 1.7466619 | P42: =P91/P111 -> 1.3794563
B45: Cash flow Statement
D47: ='Historical FS'!C44 -> Operating Activities
D48: ='Historical FS'!D45 -> Net Income | F48: [$'m] | I48: ='Historical FS'!G45 -> 62.49 | J48: ='Historical FS'!H45 -> 39.336667 | K48: ='Historical FS'!I45 -> 83.86 | L48: =L32 -> 142.08742 | M48: =M32 -> 181.24776 | N48: =N32 -> 174.59243 | O48: =O32 -> 148.71173 | P48: =P32 -> 160.22652
D49: ='Historical FS'!D46 -> Depreciation | F49: [$'m] | I49: ='Historical FS'!G46 -> 5.1 | J49: ='Historical FS'!H46 -> 5.5733333 | K49: ='Historical FS'!I46 -> 5.88 | L49: =L21 -> 6.0773333 | M49: =M21 -> 26.910667 | N49: =N21 -> 51.910667 | O49: =O21 -> 76.910667 | P49: =P21 -> 96.094
D50: ='Historical FS'!D47 -> Deferred Income Taxes | F50: [$'m] | I50: ='Historical FS'!G47 -> 1.1266667 | J50: ='Historical FS'!H47 -> 2.1133333 | K50: ='Historical FS'!I47 -> 1.6 | L50: =L29 -> 10.5 | M50: =M29 -> 10.5 | N50: =N29 -> 10.5 | O50: =O29 -> 10.5 | P50: =P29 -> 10.5
D51: ='Historical FS'!D48 -> Changes in Working Capital | F51: [$'m] | I51: ='Historical FS'!G48 -> -7.9333333 | J51: ='Historical FS'!H48 -> -0.3 | K51: ='Historical FS'!I48 -> -5.5866667 | L51: =L259 -> -1.3452151 | M51: =M259 -> -9.0454519 | N51: =N259 -> -1.8887439 | O51: =O259 -> -0.15609841 | P51: =P259 -> -4.616384
D52: ='Historical FS'!D49 -> Other | F52: [$'m] | I52: ='Historical FS'!G49 -> 10.793333 | J52: ='Historical FS'!H49 -> 10.946667 | K52: ='Historical FS'!I49 -> 16.14 | L52: =Input!L135 -> 0 | M52: =Input!M135 -> 0 | N52: =Input!N135 -> 0 | O52: =Input!O135 -> 0 | P52: =Input!P135 -> 0
D53: ='Historical FS'!D50 -> Operating Cash Flow | F53: [$'m] | I53: =SUM(I48:I52) -> 71.576667 | J53: =SUM(J48:J52) -> 57.67 | K53: =SUM(K48:K52) -> 101.89333 | L53: =SUM(L48:L52) -> 157.31954 | M53: =SUM(M48:M52) -> 209.61298 | N53: =SUM(N48:N52) -> 235.11435 | O53: =SUM(O48:O52) -> 235.9663 | P53: =SUM(P48:P52) -> 262.20414
D55: ='Historical FS'!C52 -> Investing Activities
D56: ='Historical FS'!D53 -> CAPEX | F56: [$'m] | I56: ='Historical FS'!G53 -> -5.0266667 | J56: ='Historical FS'!H53 -> -5.38 | K56: ='Historical FS'!I53 -> -5.5 | L56: =-Input!L64 -> -75 | M56: =-Input!M64 -> -550 | N56: =-Input!N64 -> -200 | O56: =-Input!O64 -> -550 | P56: =-Input!P64 -> -25.5
D57: ='Historical FS'!D54 -> Asset Dispositions | F57: [$'m] | I57: ='Historical FS'!G54 -> 0.13333333 | J57: ='Historical FS'!H54 -> 0.22666667 | K57: ='Historical FS'!I54 -> 0.7 | L57: =Input!L142 -> 0 | M57: =Input!M142 -> 0 | N57: =Input!N142 -> 0 | O57: =Input!O142 -> 0 | P57: =Input!P142 -> 0
D58: ='Historical FS'!D55 -> Other | F58: [$'m] | I58: ='Historical FS'!G55 -> -0.38666667 | J58: ='Historical FS'!H55 -> -0.28 | K58: ='Historical FS'!I55 -> -0.32 | L58: =Input!L136 -> 0 | M58: =Input!M136 -> 0 | N58: =Input!N136 -> 0 | O58: =Input!O136 -> 0 | P58: =Input!P136 -> 0
D59: ='Historical FS'!D56 -> Investing Cash Flow | F59: [$'m] | I59: =SUM(I56:I58) -> -5.28 | J59: =SUM(J56:J58) -> -5.4333333 | K59: =SUM(K56:K58) -> -5.12 | L59: =SUM(L56:L58) -> -75 | M59: =SUM(M56:M58) -> -550 | N59: =SUM(N56:N58) -> -200 | O59: =SUM(O56:O58) -> -550 | P59: =SUM(P56:P58) -> -25.5
D61: ='Historical FS'!C58 -> Financing Activities
D62: ='Historical FS'!D59 -> Revolver Issuance / (Repayment) | F62: [$'m] | I62: ='Historical FS'!G59 -> 1 | J62: ='Historical FS'!H59 -> 0 | K62: ='Historical FS'!I59 -> 0 | L62: =L334 -> 0 | M62: =M334 -> 0 | N62: =N334 -> 86.058101 | O62: =O334 -> 356.61688 | P62: =P334 -> -211.24226
D63: ='Historical FS'!D60 -> Variable Rate Long Term Debt Issuance / (Repayment) | F63: [$'m] | I63: ='Historical FS'!G60 -> 3.3333333 | J63: ='Historical FS'!H60 -> 8.3222667 | K63: ='Historical FS'!I60 -> 0 | L63: =L305-L306 -> -30.533333 | M63: =M305-M306 -> 30 | N63: =N305-N306 -> -30 | O63: =O305-O306 -> 30 | P63: =P305-P306 -> -30
D64: ='Historical FS'!D61 -> Fixed Rate Long Term Debt Issuance / (Repayment) | F64: [$'m] | I64: ='Historical FS'!G61 -> 0 | J64: ='Historical FS'!H61 -> -6.6666667 | K64: ='Historical FS'!I61 -> -8.5666667 | L64: =L297-L298 -> 0 | M64: =M297-M298 -> 54.22 | N64: =N297-N298 -> -50 | O64: =O297-O298 -> -30 | P64: =P297-P298 -> 0
D65: ='Historical FS'!D62 -> Preferred Share Issuance/ (Buy-Back) | F65: [$'m] | I65: ='Historical FS'!G62 -> 0 | J65: ='Historical FS'!H62 -> 0 | K65: ='Historical FS'!I62 -> 0 | L65: =Input!L123 -> 0 | M65: =Input!M123 -> 95 | N65: =Input!N123 -> 0 | O65: =Input!O123 -> 0 | P65: =Input!P123 -> 0
D66: ='Historical FS'!D63 -> Common Share Issuance/ (Buy-Back) | F66: [$'m] | I66: ='Historical FS'!G63 -> -5.3666667 | J66: ='Historical FS'!H63 -> -5.9333333 | K66: ='Historical FS'!I63 -> -4.6666667 | L66: =L274 -> 25 | M66: =M274 -> 0 | N66: =N274 -> -25 | O66: =O274 -> 0 | P66: =P274 -> 50
D67: ='Historical FS'!D64 -> Preferred Dividends | F67: [$'m] | I67: ='Historical FS'!G64 -> 0 | J67: ='Historical FS'!H64 -> 0 | K67: ='Historical FS'!I64 -> 0 | L67: =-L34 -> -0.082 | M67: =-M34 -> -7.207 | N67: =-N34 -> -7.207 | O67: =-O34 -> -7.207 | P67: =-P34 -> -7.207
D68: ='Historical FS'!D65 -> Common Dividends | F68: [$'m] | I68: ='Historical FS'!G65 -> -2.7866667 | J68: ='Historical FS'!H65 -> -3.0066667 | K68: ='Historical FS'!I65 -> -3.1266667 | L68: =-L282 -> -35.501356 | M68: =-M282 -> -43.510191 | N68: =-N282 -> -41.846356 | O68: =-O282 -> -35.376183 | P68: =-P282 -> -38.254881
D69: ='Historical FS'!D66 -> Other | F69: [$'m] | I69: ='Historical FS'!G66 -> -0.12 | J69: ='Historical FS'!H66 -> -0.12666667 | K69: ='Historical FS'!I66 -> -0.19333333 | L69: =Input!L137 -> 0 | M69: =Input!M137 -> 0 | N69: =Input!N137 -> 0 | O69: =Input!O137 -> 0 | P69: =Input!P137 -> 0
D70: ='Historical FS'!D67 -> Financing Cash Flow | F70: [$'m] | I70: =SUM(I62:I69) -> -3.94 | J70: =SUM(J62:J69) -> -7.4110667 | K70: =SUM(K62:K69) -> -16.553333 | L70: =SUM(L62:L69) -> -41.11669 | M70: =SUM(M62:M69) -> 128.50281 | N70: =SUM(N62:N69) -> -67.995256 | O70: =SUM(O62:O69) -> 314.0337 | P70: =SUM(P62:P69) -> -236.70414
D72: ='Historical FS'!D69 -> Change in Cash Position | F72: [$'m] | I72: =I53+I59+I70 -> 62.356667 | J72: ='Historical FS'!H69 -> 44.8256 | K72: ='Historical FS'!I69 -> 80.22 | L72: =L53+L59+L70 -> 41.202853 | M72: =M53+M59+M70 -> -211.88421 | N72: =N53+N59+N70 -> -32.880908 | O72: =O53+O59+O70 -> 0 | P72: =P53+P59+P70 -> 0
D73: ='Historical FS'!D70 -> Beginning Cash | F73: [$'m] | I73: ='Historical FS'!G70 -> 16.16 | J73: ='Historical FS'!H70 -> 78.516667 | K73: ='Historical FS'!I70 -> 123.34227 | L73: =K74 -> 203.56227 | M73: =L74 -> 244.76512 | N73: =M74 -> 32.880908 | O73: =N74 -> 0 | P73: =O74 -> 0
D74: ='Historical FS'!D71 -> Ending Cash | F74: [$'m] | I74: =SUM(I72:I73) -> 78.516667 | J74: =SUM(J72:J73) -> 123.34227 | K74: =SUM(K72:K73) -> 203.56227 | L74: =SUM(L72:L73) -> 244.76512 | M74: =SUM(M72:M73) -> 32.880908 | N74: =SUM(N72:N73) -> 0 | O74: =SUM(O72:O73) -> 0 | P74: =SUM(P72:P73) -> 0
B76: Balance Sheet
D78: ='Historical FS'!C81 -> ASSETS
D79: ='Historical FS'!D82 -> Cash and Equivalents | F79: [$'m] | I79: ='Historical FS'!G82 -> 78.516667 | J79: ='Historical FS'!H82 -> 123.34227 | K79: ='Historical FS'!I82 -> 203.56227 | L79: =L74 -> 244.76512 | M79: =M74 -> 32.880908 | N79: =N74 -> 0 | O79: =O74 -> 0 | P79: =P74 -> 0
D80: ='Historical FS'!D83 -> Accounts Receivable | F80: [$'m] | I80: ='Historical FS'!G83 -> 47.773333 | J80: ='Historical FS'!H83 -> 50.453333 | K80: ='Historical FS'!I83 -> 50.56 | L80: =L248 -> 53.189978 | M80: =M248 -> 62.74196 | N80: =N248 -> 64.48241 | O80: =O248 -> 65.228923 | P80: =P248 -> 70.209995
D81: ='Historical FS'!D84 -> Inventory | F81: [$'m] | I81: ='Historical FS'!G84 -> 11.24375 | J81: ='Historical FS'!H84 -> 12.8775 | K81: ='Historical FS'!I84 -> 13.57375 | L81: =L249 -> 14.20652 | M81: =M249 -> 14.762096 | N81: =N249 -> 15.103481 | O81: =O249 -> 15.629496 | P81: =P249 -> 16.176528
D82: ='Historical FS'!D85 -> Other | F82: [$'m] | I82: ='Historical FS'!G85 -> 18.426667 | J82: ='Historical FS'!H85 -> 19.066667 | K82: ='Historical FS'!I85 -> 19.353333 | L82: =L250 -> 21.53528 | M82: =M250 -> 21.763881 | N82: =N250 -> 22.23568 | O82: =O250 -> 23.258178 | P82: =P250 -> 23.943829
D83: ='Historical FS'!D86 -> Total Current Assets | F83: [$'m] | I83: =SUM(I79:I82) -> 155.96042 | J83: =SUM(J79:J82) -> 205.73977 | K83: =SUM(K79:K82) -> 287.04935 | L83: =SUM(L79:L82) -> 333.6969 | M83: =SUM(M79:M82) -> 132.14884 | N83: =SUM(N79:N82) -> 101.82157 | O83: =SUM(O79:O82) -> 104.1166 | P83: =SUM(P79:P82) -> 110.33035
D85: ='Historical FS'!D88 -> Net PP&E | F85: [$'m] | I85: ='Historical FS'!G88 -> 40.886667 | J85: ='Historical FS'!H88 -> 34.126667 | K85: ='Historical FS'!I88 -> 35.773333 | L85: =K85+Input!L64-Model!L49 -> 104.696 | M85: =L85+Input!M64-Model!M49 -> 627.78533 | N85: =M85+Input!N64-Model!N49 -> 775.87467 | O85: =N85+Input!O64-Model!O49 -> 1248.964 | P85: =O85+Input!P64-Model!P49 -> 1178.37
D86: ='Historical FS'!D89 -> Goodwill | F86: [$'m] | I86: ='Historical FS'!G89 -> 7.7333333 | J86: ='Historical FS'!H89 -> 7.7266667 | K86: ='Historical FS'!I89 -> 7.7333333 | L86: =K86 -> 7.7333333 | M86: =L86 -> 7.7333333 | N86: =M86 -> 7.7333333 | O86: =N86 -> 7.7333333 | P86: =O86 -> 7.7333333
D87: ='Historical FS'!D90 -> Intangibles | F87: [$'m] | I87: ='Historical FS'!G90 -> 14.66 | J87: ='Historical FS'!H90 -> 14.706667 | K87: ='Historical FS'!I90 -> 13.86 | L87: =K87 -> 13.86 | M87: =L87 -> 13.86 | N87: =M87 -> 13.86 | O87: =N87 -> 13.86 | P87: =O87 -> 13.86
D88: ='Historical FS'!D91 -> Other | F88: [$'m] | I88: ='Historical FS'!G91 -> 11.593333 | J88: ='Historical FS'!H91 -> 12.966667 | K88: ='Historical FS'!I91 -> 12.673333 | L88: =K88 -> 12.673333 | M88: =L88 -> 12.673333 | N88: =M88 -> 12.673333 | O88: =N88 -> 12.673333 | P88: =O88 -> 12.673333
D89: ='Historical FS'!D92 -> Total Long Term Assets | F89: [$'m] | I89: =SUM(I85:I88) -> 74.873333 | J89: =SUM(J85:J88) -> 69.526667 | K89: =SUM(K85:K88) -> 70.04 | L89: =SUM(L85:L88) -> 138.96267 | M89: =SUM(M85:M88) -> 662.052 | N89: =SUM(N85:N88) -> 810.14133 | O89: =SUM(O85:O88) -> 1283.2307 | P89: =SUM(P85:P88) -> 1212.6367
D91: Total Assets | F91: [$'m] | I91: =I83+I89 -> 230.83375 | J91: =J83+J89 -> 275.26643 | K91: =K83+K89 -> 357.08935 | L91: =L83+L89 -> 472.65956 | M91: =M83+M89 -> 794.20084 | N91: =N83+N89 -> 911.9629 | O91: =O83+O89 -> 1387.3473 | P91: =P83+P89 -> 1322.967
D93: ='Historical FS'!C96 -> LIABILITIES AND EQUITY
D94: ='Historical FS'!D97 -> Bank Debt - Revolver | F94: [$'m] | I94: ='Historical FS'!G97 -> 0.7 | J94: ='Historical FS'!H97 -> 0 | K94: ='Historical FS'!I97 -> 0 | L94: =L335 -> 0 | M94: =M335 -> 0 | N94: =N335 -> 86.058101 | O94: =O335 -> 442.67498 | P94: =P335 -> 231.43272
D95: ='Historical FS'!D98 -> Accounts Payable | F95: [$'m] | I95: ='Historical FS'!G98 -> 18.233333 | J95: ='Historical FS'!H98 -> 22.613333 | K95: ='Historical FS'!I98 -> 21.676667 | L95: =L253 -> 23.621158 | M95: =M253 -> 24.681291 | N95: =N253 -> 24.872796 | O95: =O253 -> 25.987138 | P95: =P253 -> 26.896688
D96: ='Historical FS'!D99 -> Other | F96: [$'m] | I96: ='Historical FS'!G99 -> 18.443333 | J96: ='Historical FS'!H99 -> 19.141667 | K96: ='Historical FS'!I99 -> 19.436667 | L96: =L254 -> 21.591655 | M96: =M254 -> 21.822229 | N96: =N254 -> 22.295614 | O96: =O254 -> 23.3202 | P96: =P254 -> 24.008022
D97: ='Historical FS'!D100 -> Total Current Liabilities | F97: [$'m] | I97: =SUM(I94:I96) -> 37.376667 | J97: =SUM(J94:J96) -> 41.755 | K97: =SUM(K94:K96) -> 41.113333 | L97: =SUM(L94:L96) -> 45.212812 | M97: =SUM(M94:M96) -> 46.50352 | N97: =SUM(N94:N96) -> 133.22651 | O97: =SUM(O94:O96) -> 491.98232 | P97: =SUM(P94:P96) -> 282.33743
D99: ='Historical FS'!D102 -> Variable Rate Long Term Debt | F99: [$'m] | I99: ='Historical FS'!G102 -> 13.266667 | J99: ='Historical FS'!H102 -> 13.353333 | K99: ='Historical FS'!I102 -> 30.533333 | L99: =L307 -> 0 | M99: =M307 -> 30 | N99: =N307 -> 0 | O99: =O307 -> 30 | P99: =P307 -> 0
D100: ='Historical FS'!D103 -> Fixed Rate Long Term Debt | F100: [$'m] | I100: ='Historical FS'!G103 -> 52.526667 | J100: ='Historical FS'!H103 -> 57.366667 | K100: ='Historical FS'!I103 -> 25.78 | L100: =L299 -> 25.78 | M100: =M299 -> 80 | N100: =N299 -> 30 | O100: =O299 -> 0 | P100: =P299 -> 0
D101: ='Historical FS'!D104 -> Deferred Income Taxes | F101: [$'m] | I101: ='Historical FS'!G104 -> 0.93333333 | J101: ='Historical FS'!H104 -> 1.18 | K101: ='Historical FS'!I104 -> 1.92 | L101: =K101+L50 -> 12.42 | M101: =L101+M50 -> 22.92 | N101: =M101+N50 -> 33.42 | O101: =N101+O50 -> 43.92 | P101: =O101+P50 -> 54.42
D102: ='Historical FS'!D105 -> Other | F102: [$'m] | I102: ='Historical FS'!G105 -> 21.6 | J102: ='Historical FS'!H105 -> 26.313333 | K102: ='Historical FS'!I105 -> 27.16 | L102: =K102 -> 27.16 | M102: =L102 -> 27.16 | N102: =M102 -> 27.16 | O102: =N102 -> 27.16 | P102: =O102 -> 27.16
D103: ='Historical FS'!D106 -> Total Long Term Liabilities | F103: [$'m] | I103: =SUM(I99:I102) -> 88.326667 | J103: =SUM(J99:J102) -> 98.213333 | K103: =SUM(K99:K102) -> 85.393333 | L103: =SUM(L99:L102) -> 65.36 | M103: =SUM(M99:M102) -> 160.08 | N103: =SUM(N99:N102) -> 90.58 | O103: =SUM(O99:O102) -> 101.08 | P103: =SUM(P99:P102) -> 81.58
D105: ='Historical FS'!D108 -> Total Liabilities | F105: [$'m] | I105: =I97+I103 -> 125.70333 | J105: =J97+J103 -> 139.96833 | K105: =K97+K103 -> 126.50667 | L105: =L97+L103 -> 110.57281 | M105: =M97+M103 -> 206.58352 | N105: =N97+N103 -> 223.80651 | O105: =O97+O103 -> 593.06232 | P105: =P97+P103 -> 363.91743
D107: ='Historical FS'!D110 -> Preferred Shares | F107: [$'m] | I107: ='Historical FS'!G110 -> 0.42666667 | J107: ='Historical FS'!H110 -> 0.42666667 | K107: ='Historical FS'!I110 -> 1.0933333 | L107: =L266 -> 1.0933333 | M107: =M266 -> 96.093333 | N107: =N266 -> 96.093333 | O107: =O266 -> 96.093333 | P107: =P266 -> 96.093333
D108: ='Historical FS'!D111 -> Common Shares | F108: [$'m] | I108: ='Historical FS'!G111 -> 24.345333 | J108: ='Historical FS'!H111 -> 24.801267 | K108: ='Historical FS'!I111 -> 23.0916 | L108: =L275 -> 48.0916 | M108: =M275 -> 48.0916 | N108: =N275 -> 23.0916 | O108: =O275 -> 23.0916 | P108: =P275 -> 73.0916
D109: ='Historical FS'!D112 -> Retained Earnings | F109: [$'m] | I109: ='Historical FS'!G112 -> 19.637083 | J109: ='Historical FS'!H112 -> 11.190833 | K109: ='Historical FS'!I112 -> 23.340417 | L109: =L283 -> 129.84449 | M109: =M283 -> 260.37506 | N109: =N283 -> 385.91413 | O109: =O283 -> 492.04268 | P109: =P283 -> 606.80732
D110: ='Historical FS'!D113 -> Other | F110: [$'m] | I110: ='Historical FS'!G113 -> 60.721333 | J110: ='Historical FS'!H113 -> 98.879333 | K110: ='Historical FS'!I113 -> 183.05733 | L110: =K110 -> 183.05733 | M110: =L110 -> 183.05733 | N110: =M110 -> 183.05733 | O110: =N110 -> 183.05733 | P110: =O110 -> 183.05733
D111: ='Historical FS'!D114 -> Shareholder's Equity | F111: [$'m] | I111: =SUM(I107:I110) -> 105.13042 | J111: =SUM(J107:J110) -> 135.2981 | K111: =SUM(K107:K110) -> 230.58268 | L111: =SUM(L107:L110) -> 362.08675 | M111: =SUM(M107:M110) -> 587.61732 | N111: =SUM(N107:N110) -> 688.15639 | O111: =SUM(O107:O110) -> 794.28494 | P111: =SUM(P107:P110) -> 959.04959
D113: ='Historical FS'!D116 -> Total Liabilities and Equity | F113: [$'m] | I113: =I105+I111 -> 230.83375 | J113: =J105+J111 -> 275.26643 | K113: =K105+K111 -> 357.08935 | L113: =L105+L111 -> 472.65956 | M113: =M105+M111 -> 794.20084 | N113: =N105+N111 -> 911.9629 | O113: =O105+O111 -> 1387.3473 | P113: =P105+P111 -> 1322.967
D115: Accuracy Check | F115: =ROUND(SUM(I115:P115),0) -> 0 | I115: =I91-I113 -> 3.126388e-13 | J115: =J91-J113 -> 0 | K115: =K91-K113 -> 0 | L115: =L91-L113 -> 0 | M115: =M91-M113 -> 0 | N115: =N91-N113 -> 0 | O115: =O91-O113 -> 0 | P115: =P91-P113 -> 0
A117: Calculations & Schedules
B119: Revenue Schedule
C121: Product-70g
D122: =Input!D28 -> Production Capacity | F122: [units] | L122: =Input!L28 -> 35000000 | M122: =Input!M28 -> 35000000 | N122: =Input!N28 -> 35000000 | O122: =Input!O28 -> 33000000 | P122: =Input!P28 -> 35000000
D124: =Input!D29 -> Price | F124: [$/unit] | K124: =Input!K29 -> 15 | L124: =K124*(1+L126) -> 15.375 | M124: =L124*(1+M126) -> 15.71325 | N124: =M124*(1+N126) -> 16.027515 | O124: =N124*(1+O126) -> 16.235873 | P124: =O124*(1+P126) -> 16.64177
D126: =Input!D30 -> Pricing growth | F126: [%] | L126: =Input!L30 -> 0.025 | M126: =Input!M30 -> 0.022 | N126: =Input!N30 -> 0.02 | O126: =Input!O30 -> 0.013 | P126: =Input!P30 -> 0.025
D128: Volume | F128: [units] | K128: =(K12-K151)*Million/K124 -> 30766667 | L128: =K128*(1+L130) -> 31689667 | M128: =L128*(1+M130) -> 32798805 | N128: =M128*(1+N130) -> 33454781 | O128: =N128*(1+O130) -> 34291151 | P128: =O128*(1+P130) -> 35319885
D130: Volume growth | F130: [%] | L130: =Input!L31 -> 0.03 | M130: =Input!M31 -> 0.035 | N130: =Input!N31 -> 0.02 | O130: =Input!O31 -> 0.025 | P130: =Input!P31 -> 0.03
D132: Actual Quantity produced | F132: [units] | L132: =MIN(L122,L128) -> 31689667 | M132: =MIN(M122,M128) -> 32798805 | N132: =MIN(N122,N128) -> 33454781 | O132: =MIN(O122,O128) -> 33000000 | P132: =MIN(P122,P128) -> 35000000
D134: Total Revenue-70g | K134: =(K124*K128)/Million -> 461.5 | L134: =(L124*L132)/Million -> 487.22862 | M134: =(M124*M132)/Million -> 515.37582 | N134: =(N124*N132)/Million -> 536.19701 | O134: =(O124*O132)/Million -> 535.7838 | P134: =(P124*P132)/Million -> 582.46193
C136: Product-100g
D137: Production Capacity | F137: [units] | M137: =Input!M34 -> 4600000 | N137: =Input!N34 -> 4600000 | O137: =Input!O34 -> 4000000 | P137: =Input!P34 -> 3800000
D139: Price | F139: [$/unit] | M139: =Input!M35 -> 18 | N139: =M139*(1+N141) -> 18.504 | O139: =N139*(1+O141) -> 18.744552 | P139: =O139*(1+P141) -> 19.119443
D141: Pricing growth | F141: [%] | N141: =Input!N36 -> 0.028 | O141: =Input!O36 -> 0.013 | P141: =Input!P36 -> 0.02
...
